CHANGELOG.txt
LICENCE.txt
MANIFEST.in
README.md
setup.py
voix/__init__.py
voix.egg-info/PKG-INFO
voix.egg-info/SOURCES.txt
voix.egg-info/dependency_links.txt
voix.egg-info/requires.txt
voix.egg-info/top_level.txt