Metadata-Version: 2.1
Name: voix
Version: 0.1
Summary: A tiny package that can generate voice for you
Home-page: UNKNOWN
Author: Tahmid Ahnaf
Author-email: tahmidahnafxtra@gmail.com
License: MIT
Keywords: voix,voice,sound,speak,speaker,sound generator,voice generator,text to speech,tts,translate
Platform: UNKNOWN
Classifier: Development Status :: 5 - Production/Stable
Classifier: Intended Audience :: Education
Classifier: Operating System :: Microsoft :: Windows :: Windows 10
Classifier: License :: OSI Approved :: MIT License
Classifier: Programming Language :: Python :: 3
